mongoredis.py
setup.py
mongoredis.egg-info/PKG-INFO
mongoredis.egg-info/SOURCES.txt
mongoredis.egg-info/dependency_links.txt
mongoredis.egg-info/not-zip-safe
mongoredis.egg-info/requires.txt
mongoredis.egg-info/top_level.txt