Metadata-Version: 1.0
Name: mongoredis
Version: 0.1
Summary: Redis emulator for mongodb
Home-page: https://github.com/pnegahdar/mongoredis
Author: Parham Negahdar
Author-email: pnegahdar@gmail.com
License: See License
Platform: any
Classifier: Environment :: Web Environment
Classifier: Intended Audience :: Developers
Classifier: License :: OSI Approved :: MIT License
Classifier: Operating System :: OS Independent
Classifier: Programming Language :: Python
Classifier: Topic :: Internet :: WWW/HTTP :: Dynamic Content
Classifier: Topic :: Software Development :: Libraries :: Python Modules
